blyzer/__init__.py
blyzer/analitics/__init__.py
blyzer/analitics/trajectory/calc_features.py
blyzer/analitics/trajectory/helper.py
blyzer/analitics/trajectory/lineintersect.py
blyzer/analitics/trajectory/readme.txt
blyzer/client2/.gitignore
blyzer/client2/__init__.py
blyzer/client2/a.out
blyzer/client2/dog_extractor.py
blyzer/client2/gui/__init__.py
blyzer/client2/gui/about_widget.py
blyzer/client2/gui/client_main_gui.py
blyzer/client2/gui/new_project_dialog.py
blyzer/client2/gui/resources/blyzer_logo.ico
blyzer/client2/gui/resources/blyzer_logo.png
blyzer/client2/gui/resources/digiratory_logo.png
blyzer/client2/gui/resources/leti_logo_eng_2019.png
blyzer/client2/gui/resources/tech4animals_logo.jpg
blyzer/client2/gui/resources/unihaifa-300x160.jpg
blyzer/client2/gui/settings_widget.py
blyzer/client2/gui/statistic_item_widget.py
blyzer/client2/gui/statistic_widget.py
blyzer/client2/gui/summary_widget.py
blyzer/client2/gui/videowidget.py
blyzer/client2/neural_processor.py
blyzer/client2/preview.py
blyzer/client2/project_manager.py
blyzer/client2/remote_neural_processor.py
blyzer/client2/run.py
blyzer/client2/statistic_holder.py
blyzer/client2/tools/.gitkeep
blyzer/client2/tools/demo_tail_angle.py
blyzer/client2/tools/vid_analysis.py
blyzer/client2/tools/Vienna_lines_screens.py
blyzer/client2/video_media_source.py
blyzer/common/__init__.py
blyzer/common/annotation.py
blyzer/common/blyzer_project.py
blyzer/common/object.py
blyzer/common/saver.py
blyzer/common/settings.py
blyzer/common/singleton.py
blyzer/common/summary.py
blyzer/common/trajectory.py
blyzer/common/video.py
blyzer/server/__init__.py
blyzer/server/model_controller.py
blyzer/server/model_wrappers/__init__.py
blyzer/server/model_wrappers/base_wrapper.py
blyzer/server/model_wrappers/dcl_wrapper.py
blyzer/server/model_wrappers/od_wrapper.py
blyzer/server/python_api/blyzer_api.py
blyzer/server/README.txt
blyzer/server/start.py
blyzer/tools/__init__.py
blyzer/tools/annotation_tool.py
blyzer/tools/auto_get_st.py
automatic_behavior_analysis-0.0.21.dist-info/entry_points.txt
automatic_behavior_analysis-0.0.21.dist-info/WHEEL
automatic_behavior_analysis-0.0.21.dist-info/METADATA
automatic_behavior_analysis-0.0.21.dist-info/RECORD
