Metadata-Version: 2.1
Name: automatic-behavior-analysis
Version: 0.0.21
Summary: Program complex for automated behavior analysis
Home-page: https://gitlab.com/digiratory/automatic-behavior-analysis/
Author: Aleksandr Sinitca
Author-email: siniza.s.94@gmail.com
Requires-Python: >=3.6,<4.0
Classifier: Programming Language :: Python :: 3
Classifier: Programming Language :: Python :: 3.6
Classifier: Programming Language :: Python :: 3.7
Classifier: Programming Language :: Python :: 3.8
Classifier: Topic :: Scientific/Engineering :: Artificial Intelligence
Classifier: Topic :: Scientific/Engineering :: Medical Science Apps.
Requires-Dist: PyQt5
Requires-Dist: appdirs
Requires-Dist: imageio
Requires-Dist: matplotlib
Requires-Dist: numpy
Requires-Dist: opencv-python
Requires-Dist: pandas
Requires-Dist: scipy
Project-URL: Repository, https://gitlab.com/digiratory/automatic-behavior-analysis/
